biocolabsdk/.DS_Store
biocolabsdk/__init__.py
biocolabsdk/connector.py
biocolabsdk/identity.py
biocolabsdk/util.py
biocolabsdk-1.0.8.dist-info/LICENSE
biocolabsdk-1.0.8.dist-info/METADATA
biocolabsdk-1.0.8.dist-info/WHEEL
biocolabsdk-1.0.8.dist-info/RECORD
