Metadata-Version: 2.1
Name: biocolabsdk
Version: 1.0.8
Summary: A set of python modules for accessing BioTuring Ecosystem on BioStudio private server
Author: BioTuring
Author-email: support@bioturing.com
Requires-Python: >=3.7,<4.0
Classifier: Programming Language :: Python :: 3
Classifier: Programming Language :: Python :: 3.7
Classifier: Programming Language :: Python :: 3.8
Classifier: Programming Language :: Python :: 3.9
Classifier: Programming Language :: Python :: 3.10
Classifier: Programming Language :: Python :: 3.11
Classifier: Programming Language :: Python :: 3.12
Requires-Dist: bioflex (>=1.1,<2.0)
Requires-Dist: bioturing-connector (>=1.8,<2.0)
Requires-Dist: requests (>=2.31,<3.0)
